nesse/__init__.py
nesse/charge_propagation.py
nesse/constants.py
nesse/event.py
nesse/field.py
nesse/interp.pyx
nesse/interp_3d.py
nesse/mobility.py
nesse/plotting.py
nesse/quasiparticles.py
nesse/silicon.py
nesse/simulation.py
nesse-0.2.2.dist-info/LICENSE
nesse-0.2.2.dist-info/METADATA
nesse-0.2.2.dist-info/WHEEL
nesse-0.2.2.dist-info/top_level.txt
nesse-0.2.2.dist-info/RECORD
