Metadata-Version: 2.1
Name: nesse
Version: 0.2.2
Summary: A solid state detector simulation developed for the Nab experiment.
Author-email: RJ Taylor <rjtaylo2@ncsu.edu>, Leendert Hayen <hayen@lpccaen.in2p3.fr>
Project-URL: Homepage, https://github.com/rjtayl/nesse
Project-URL: Bug Tracker, https://github.com/rjtayl/nesse/issues
Classifier: Programming Language :: Python :: 3
Classifier: License :: OSI Approved :: MIT License
Classifier: Operating System :: OS Independent
Classifier: Intended Audience :: Science/Research
Classifier: Topic :: Scientific/Engineering :: Physics
Requires-Python: >=3.7
License-File: LICENSE
Requires-Dist: numpy ==1.24.3
Requires-Dist: scipy
Requires-Dist: tqdm
Requires-Dist: Cython
Requires-Dist: matplotlib
Requires-Dist: numba
Requires-Dist: h5py
Requires-Dist: uproot ==4.3.7
Requires-Dist: pandas
Requires-Dist: pyMSVC
